talmud_debts/__init__.py
talmud_debts-0.1.4.dist-info/LICENSE
talmud_debts-0.1.4.dist-info/METADATA
talmud_debts-0.1.4.dist-info/WHEEL
talmud_debts-0.1.4.dist-info/top_level.txt
talmud_debts-0.1.4.dist-info/RECORD
